Workbook

Sheet 前提条件
A1: 西麻布4丁目 土地（FACE西麻布） 収支試算 前提条件 ※青字は変更可
A3: 項目 | B3: 値 | C3: 備考
A4: 土地面積(㎡) | B4: 330.99 | C4: 登記簿。実測なし → 要確定測量
A5: 土地価格(円) | B5: 2500000000 | C5: 募集価格25億円(税込)。価格交渉可
A6: 近隣商業地域の面積割合 | B6: 0.15 | C6: 用途地域図で要確認。一住(60/300)+近商(80/400)の跨り
A7: 容積率 一住 | B7: 3
A8: 容積率 近商 | B8: 4
A9: 前面道路幅員(m) | B9: 7.1 | C9: 西側公道7.1m。南側私道4mは容積計算に不使用
A10: 道路幅員係数 一住 | B10: 0.4 | C10: 住居系 0.4
A11: 道路幅員係数 近商 | B11: 0.6 | C11: その他 0.6
A12: 既存建物延床(㎡) | B12: 878.57 | C12: RC B1/3F 2002年
A13: 現行年間賃料(円) | B13: 95700000 | C13: レントロール 7,975,000円/月
A14: 取得〜退去 月数 | B14: 3 | C14: 2026/11取得→2027/1末退去想定
A15: 仲介手数料率 | B15: 0.03 | C15: 税抜。別途消費税
A16: 土地 固定資産税評価(円) | B16: 695100000 | C16: 公示地価300万/㎡×0.7 想定
A17: 登録免許税率(土地) | B17: 0.015
A18: 不動産取得税率(宅地特例後) | B18: 0.015 | C18: 3%×1/2
A19: その他取得費用(円) | B19: 15000000 | C19: 司法書士・印紙・測量・調査
A20: 固都税 年額(円) | B20: 13000000 | C20: 土地+既存建物
A21: 解体 坪単価(円) | B21: 150000 | C21: RC・地下あり 東京
A22: 解体 追加費用(円) | B22: 20000000 | C22: アスベスト・埋戻し・近隣対策
A23: 設計監理率 | B23: 0.05 | C23: 本体工事比
A24: 外構・調査・近隣対策等(円) | B24: 30000000
A25: 予備費率 | B25: 0.03 | C25: 本体工事比
A26: 金利(年) | B26: 0.02
A27: 融資手数料率 | B27: 0.005
A29: 計算値
A30: 土地面積(坪) | B30: ='前提条件'!$B$4/3.30579
A31: 土地 坪単価(万円) | B31: ='前提条件'!$B$5/B30/10000
A32: 許容容積率(道路幅員反映) | B32: =(1-'前提条件'!$B$6)*MIN('前提条件'!$B$7,'前提条件'!$B$9*'前提条件'!$B$10)+'前提条件'!$B$6*MIN('前提条件'!$B$8,'前提条件'!$B$9*'前提条件'!$B$11)
A33: 容積対象床面積(㎡) | B33: ='前提条件'!$B$4*B32
A34: 既存建物解体費(円) | B34: ='前提条件'!$B$12/3.30579*'前提条件'!$B$21+'前提条件'!$B$22
A35: 取得諸経費(円) | B35: ='前提条件'!$B$5*'前提条件'!$B$15*1.1+'前提条件'!$B$16*('前提条件'!$B$17+'前提条件'!$B$18)+'前提条件'!$B$19
A36: 退去までの賃料収入(円) | B36: ='前提条件'!$B$13/12*'前提条件'!$B$14

Sheet 分譲マンション
A1: 分譲マンション 収支（数式） ※青字は変更可
A3: 前提 | B3: 値 | C3: 備考
A4: 延床/容積対象 倍率 | B4: 1.25 | C4: 共用廊下・階段・EV・地下住宅1/3 等の不算入分
A5: 専有/容積対象 倍率 | B5: 0.85
A6: 販売坪単価(円) | B6: 15000000 | C6: 港区2026年1-4月平均758万/坪。西麻布小規模高級で1,500万想定
A7: 本体工事 坪単価(円) | B7: 2000000 | C7: RC造 東京 小規模高級仕様
A8: 販売経費率(売上比) | B8: 0.05 | C8: 広告・販売手数料
A9: 事業期間(月) | B9: 27 | C9: 退去3+解体3+工事18+引渡3
A11: 項目 | B11: 金額(円) | C11: 算式
A12: 土地代 | B12: ='前提条件'!$B$5
A13: 取得諸経費 | B13: ='前提条件'!$B$35
A14: 固都税(事業期間) | B14: ='前提条件'!$B$20*$B$9/12
A15: 既存建物解体 | B15: ='前提条件'!$B$34
A16: 退去までの賃料収入 | B16: =-'前提条件'!$B$36
A17: 本体工事費 | B17: ='前提条件'!$B$33*$B$4/3.30579*$B$7
A18: 設計監理 | B18: =B17*'前提条件'!$B$23
A19: 外構・調査・近隣対策等 | B19: ='前提条件'!$B$24
A20: 予備費 | B20: =B17*'前提条件'!$B$25
A21: 販売経費 | B21: =B28*$B$8
A22: 金利・融資手数料 | B22: =(SUM(B12:B16)+SUM(B18:B21))*'前提条件'!$B$26*$B$9/12+B17*'前提条件'!$B$26*$B$9/12*0.5+SUM(B12:B21)*'前提条件'!$B$27
A23: 総事業費 | B23: =SUM(B12:B22)
A25: 収入・指標 | B25: 値
A26: 専有面積(㎡) | B26: ='前提条件'!$B$33*$B$5
A27: 専有面積(坪) | B27: =B26/3.30579
A28: 売上高(円) | B28: =B27*$B$6
A29: 事業利益(円) | B29: =B28-B23
A30: 利益率(売上比) | B30: =B29/B28
A31: 利益率(総事業費比) | B31: =B29/B23
A32: 損益分岐 販売坪単価(円) | B32: =B23/B27
A33: 想定戸数(約100㎡/戸) | B33: =ROUND(B26/100,0)

Sheet ホテル
A1: ホテル 収支（数式） ※青字は変更可。初期値はアップスケール想定
A3: 前提 | B3: 値 | C3: 備考
A4: 延床/容積対象 倍率 | B4: 1.06 | C4: ホテルは廊下も容積算入。機械室のみ不算入
A5: 延床/客室(㎡/室) | B5: 36 | C5: 宿泊特化28 / アップスケール36 / ラグジュアリー50
A6: ADR(円) | B6: 45000 | C6: 宿泊特化28,000 / アップスケール45,000 / ラグジュアリー90,000
A7: 稼働率 | B7: 0.8
A8: 料飲・その他売上比率 | B8: 0.08 | C8: 客室売上比
A9: 所有者NOI率(総売上比) | B9: 0.26 | C9: 賃貸借型の賃料 / MC型のGOP−手数料−FF&E積立
A10: 本体工事 坪単価(円) | B10: 2200000
A11: FF&E(円/室) | B11: 4000000
A12: 開業準備費(円) | B12: 30000000
A13: 事業期間(月) | B13: 27
A14: 還元利回り(Cap) | B14: 0.045 | C14: CBRE 2026/3 東京ホテル4.2%に保守性を上乗せ
A15: 運営時固都税倍率 | B15: 1.6 | C15: 新築建物分の増加
A17: 延床面積(㎡) | B17: ='前提条件'!$B$33*$B$4
A18: 客室数 | B18: =INT($B$17/$B$5)
A20: 項目 | B20: 金額(円)
A21: 土地代 | B21: ='前提条件'!$B$5
A22: 取得諸経費 | B22: ='前提条件'!$B$35
A23: 固都税(事業期間) | B23: ='前提条件'!$B$20*$B$13/12
A24: 既存建物解体 | B24: ='前提条件'!$B$34
A25: 退去までの賃料収入 | B25: =-'前提条件'!$B$36
A26: 本体工事費 | B26: =$B$17/3.30579*$B$10
A27: 設計監理 | B27: =B26*'前提条件'!$B$23
A28: FF&E | B28: =$B$18*$B$11
A29: 外構・調査・近隣対策等 | B29: ='前提条件'!$B$24
A30: 開業準備費 | B30: =$B$12
A31: 予備費 | B31: =B26*'前提条件'!$B$25
A32: 金利・融資手数料 | B32: =(SUM(B21:B25)+SUM(B27:B31))*'前提条件'!$B$26*$B$13/12+B26*'前提条件'!$B$26*$B$13/12*0.5+SUM(B21:B31)*'前提条件'!$B$27
A33: 総事業費 | B33: =SUM(B21:B32)
A35: 収入・指標 | B35: 値
A36: RevPAR(円) | B36: =$B$6*$B$7
A37: 客室売上(円/年) | B37: =$B$18*$B$6*$B$7*365
A38: 総売上(円/年) | B38: =B37*(1+$B$8)
A39: 所有者NOI(円/年) | B39: =B38*$B$9-'前提条件'!$B$20*$B$15
A40: NOI利回り(総事業費比) | B40: =B39/B33
A41: 収益価格(円) | B41: =B39/$B$14
A42: 含み損益(収益価格−総事業費) | B42: =B41-B33
A43: 損益分岐ADR(円) | B43: =((B33*$B$14+'前提条件'!$B$20*$B$15)/$B$9/(1+$B$8))/($B$18*$B$7*365)

Sheet 用途比較
A1: 用途別 収支比較（土地25億円・基準ケース、feasibility.py の計算値）
A3: 用途 | B3: 総事業費 | C3: 年間売上/売上高 | D3: 年間NOI/事業利益 | E3: 利回り/利益率 | F3: 収益価格 | G3: 含み損益 | H3: 備考
A4: 分譲マンション | B4: 38.909734 | C4: 38.476277 | D4: -0.43345711 | E4: -0.011265568 | H4: 専有257坪・9戸
A5: ホテル（宿泊特化） | B5: 36.901374 | C5: 3.3106157 | D5: 0.65276008 | E5: 0.017689317 | F5: 14.50578 | G5: -22.395594 | H5: 37室・ADR28,000円・稼働85%
A6: ホテル（アップスケール） | B6: 37.85922 | C6: 4.115448 | D6: 0.86201648 | E6: 0.022768998 | F6: 19.155922 | G6: -18.703298 | H6: 29室・ADR45,000円・稼働80%
A7: ホテル（ラグジュアリー） | B7: 39.827412 | C7: 5.711958 | D7: 1.2771091 | E7: 0.032066083 | F7: 28.380202 | G7: -11.44721 | H7: 21室・ADR90,000円・稼働72%
A8: 賃貸レジデンス | B8: 36.88973 | C8: 0.64332335 | D8: 0.30665868 | E8: 0.0083128471 | F8: 8.2880725 | G8: -28.601657 | H8: 貸室257坪・22,000円/坪
A9: 店舗ビル建替 | B9: 35.548039 | C9: 1.0194674 | D9: 0.65854732 | E9: 0.01852556 | F9: 16.463683 | G9: -19.084356 | H9: 貸室257坪・36,000円/坪
A10: 現況保有（再テナント） | B10: 26.18353 | C10: 0.8852184 | D10: 0.63095748 | E10: 0.024097495 | F10: 18.027357 | G10: -8.1561734 | H10: 再募集後ベース
A12: ※ 保有型は「収益価格＝NOI÷還元利回り」と総事業費の差を含み損益として表示。ホテル4.5%・賃貸住宅3.7%・店舗4.0%・現況保有3.5%。

Sheet 感度分析
A1: 分譲マンション 事業利益（億円）と利益率 行：販売坪単価 / 列：土地価格
A3: 販売坪単価 | B3: 土地18億 利益 | C3: 土地20億 利益 | D3: 土地22億 利益 | E3: 土地25億 利益 | F3: 土地18億 利益率 | G3: 土地20億 利益率 | H3: 土地22億 利益率 | I3: 土地25億 利益率
A4: 1,200万円/坪 | B4: -0.13216162 | C4: -2.3014616 | D4: -4.4707616 | E4: -7.7247116 | F4: -0.0042936073 | G4: -0.074768851 | H4: -0.14524409 | I4: -0.25095696
A5: 1,400万円/坪 | B5: 4.7286747 | C5: 2.5593747 | D5: 0.39007472 | E5: -2.8638753 | F5: 0.13167691 | G5: 0.071269556 | H5: 0.010862205 | I5: -0.079748823
A6: 1,500万円/坪 | B6: 7.1590929 | C6: 4.9897929 | D6: 2.8204929 | E6: -0.43345711 | F6: 0.18606511 | G6: 0.12968492 | H6: 0.073304725 | I6: -0.011265568
A7: 1,600万円/坪 | B7: 9.5895111 | C7: 7.4202111 | D7: 5.2509111 | E7: 1.9969611 | F7: 0.23365479 | G7: 0.18079836 | H7: 0.12794193 | I7: 0.04865728
A8: 1,800万円/坪 | B8: 14.450347 | C8: 12.281047 | D8: 10.111747 | E8: 6.8577974 | F8: 0.31297093 | G8: 0.26598743 | H8: 0.21900394 | I8: 0.14852869
A9: 2,000万円/坪 | B9: 19.311184 | C9: 17.141884 | D9: 14.972584 | E9: 11.718634 | F9: 0.37642384 | G9: 0.33413869 | H9: 0.29185354 | I9: 0.22842582
A12: 容積率ケース（分譲・坪1,500万・土地25億）
A13: ケース | B13: 許容容積率 | C13: 専有面積(坪) | D13: 事業利益(億) | E13: 利益率
A14: 保守（全て一住・道路幅員284%） | B14: 2.84 | C14: 241.70013 | D14: -2.0539956 | E14: -0.056654104
A15: 基準（近商15%） | B15: 3.014 | C15: 256.50851 | D15: -0.43345711 | E15: -0.011265568
A16: 上振れ（近商40%） | B16: 3.304 | C16: 281.18916 | D16: 2.2674404 | E16: 0.053758365

Sheet 残余法
A1: 残余法による土地価格（用途別に支払可能な上限）
A3: 用途・条件 | B3: 土地価格(億円) | C3: 坪単価(万円)
A4: 分譲(坪1,500万・利益率15%) | B4: 19.279354 | C4: 1925.5414
A5: 分譲(坪1,800万・利益率15%) | B5: 24.937369 | C5: 2490.6404
A6: ホテル(アップスケール・収益価格=事業費) | B6: 7.7563749 | C6: 774.67436
A7: ホテル(ラグジュアリー・収益価格=事業費) | B7: 14.446172 | C7: 1442.8234
A8: 賃貸レジデンス(収益価格=事業費) | B8: 1.7347235e-17 | C8: 1.7325694e-15
A9: 店舗ビル建替(収益価格=事業費) | B9: 7.4050558 | C9: 739.58608
A10: 現況保有(収益価格=取得費) | B10: 17.104382 | C10: 1708.3143
A12: 募集価格 25.00億円 = 2,497万円/坪
